<r>
<q>
<a n="11">قَوْمَ فِرْعَوْنَ ۚ أَلَا يَتَّقُونَ.</a>
<a n="12">قَالَ رَبِّ إِنِّىٓ أَخَافُ أَن يُكَذِّبُونِ.</a>
<a n="13">وَيَضِيقُ صَدْرِى وَلَا يَنطَلِقُ لِسَانِى فَأَرْسِلْ إِلَىٰ هَٰرُونَ.</a>
<a n="14">وَلَهُمْ عَلَىَّ ذَنۢبٌۭ فَأَخَافُ أَن يَقْتُلُونِ.</a>
<a n="15">قَالَ كَلَّا ۖ فَٱذْهَبَا بِـَٔايَٰتِنَآ ۖ إِنَّا مَعَكُم مُّسْتَمِعُونَ.</a>
<a n="16">فَأْتِيَا فِرْعَوْنَ فَقُولَآ إِنَّا رَسُولُ رَبِّ ٱلْعَٰلَمِينَ.</a>
<a n="17">أَنْ أَرْسِلْ مَعَنَا بَنِىٓ إِسْرَٰٓءِيلَ.</a>
<a n="18">قَالَ أَلَمْ نُرَبِّكَ فِينَا وَلِيدًۭا وَلَبِثْتَ فِينَا مِنْ عُمُرِكَ سِنِينَ.</a>
<a n="19">وَفَعَلْتَ فَعْلَتَكَ ٱلَّتِى فَعَلْتَ وَأَنتَ مِنَ ٱلْكَٰفِرِينَ.</a>
<a n="20">قَالَ فَعَلْتُهَآ إِذًۭا وَأَنَا۠ مِنَ ٱلضَّآلِّينَ.</a>
</q>
</r>
